README.txt
setup.py
sqlex/__init__.py
sqlex/main.py
sqlex/model.py
sqlex.egg-info/PKG-INFO
sqlex.egg-info/SOURCES.txt
sqlex.egg-info/dependency_links.txt
sqlex.egg-info/entry_points.txt
sqlex.egg-info/not-zip-safe
sqlex.egg-info/top_level.txt