Metadata-Version: 1.0
Name: sqlex
Version: 0.0
Summary: sql(ite) explorer/exporter
Home-page: http://k0s.org/hg/sqlex
Author: Jeff Hammel
Author-email: k0scist@gmail.com
License: UNKNOWN
Platform: UNKNOWN
